LICENSE
README.md
setup.py
data_anonymizer/__init__.py
data_anonymizer/__main__.py
data_anonymizer/cli.py
data_anonymizer/config.py
data_anonymizer/config_generator.py
data_anonymizer.egg-info/PKG-INFO
data_anonymizer.egg-info/SOURCES.txt
data_anonymizer.egg-info/dependency_links.txt
data_anonymizer.egg-info/entry_points.txt
data_anonymizer.egg-info/requires.txt
data_anonymizer.egg-info/top_level.txt
data_anonymizer/field_types/__init__.py
data_anonymizer/field_types/city.py
data_anonymizer/field_types/county.py
data_anonymizer/field_types/custom.py
data_anonymizer/field_types/custom_address.py
data_anonymizer/field_types/custom_name.py
data_anonymizer/field_types/date_time.py
data_anonymizer/field_types/email_address.py
data_anonymizer/field_types/field_type_factory.py
data_anonymizer/field_types/first_name.py
data_anonymizer/field_types/float_range.py
data_anonymizer/field_types/full_address.py
data_anonymizer/field_types/full_name.py
data_anonymizer/field_types/int_range.py
data_anonymizer/field_types/last_name.py
data_anonymizer/field_types/normal_int.py
data_anonymizer/field_types/options.py
data_anonymizer/field_types/safe_harbor_age.py
data_anonymizer/field_types/ssn.py
data_anonymizer/field_types/street_address.py
data_anonymizer/field_types/zip.py
data_anonymizer/field_types/decorators/__init__.py
data_anonymizer/field_types/decorators/text_formatter.py