Metadata-Version: 2.1
Name: data-anonymizer
Version: 0.3.0
Summary: A tool to anonymize data within a CSV
Home-page: https://github.com/calebdinsmore/data-anonymizer
Author: Caleb Dinsmore
Author-email: caleb.dinsmore@edusource.us
License: MIT
Platform: UNKNOWN
Classifier: Programming Language :: Python :: 3
Classifier: License :: OSI Approved :: MIT License
Classifier: Operating System :: OS Independent
License-File: LICENSE
